sardou/__init__.py
sardou/requirements.py
sardou/sardou.py
sardou/validation.py
sardou-0.3.0.dist-info/METADATA
sardou-0.3.0.dist-info/WHEEL
sardou-0.3.0.dist-info/top_level.txt
sardou-0.3.0.dist-info/RECORD
