Metadata-Version: 2.4
Name: Sardou
Version: 0.3.0
Summary: Sardou TOSCA Library
Author-email: Jay DesLauriers <j.deslauriers@westminster.ac.uk>
Requires-Dist: ruamel.yaml
